{
    "molecule": "CCarb_927",
    "atoms": [
        {
            "index": 0,
            "element": "C",
            "charge": -0.42307814495589646,
            "dipole": [
                0.023663127354353428,
                0.05797711630729043,
                0.04405211995696251
            ],
            "quadrupole": [
                [
                    -5.0709192525460995,
                    -5.12031870790079,
                    -0.05504401544956996
                ],
                [
                    -5.12031870790079,
                    -0.006968646199224837,
                    -5.0878761680967814
                ],
                [
                    -0.05504401544956996,
                    -5.0878761680967814,
                    -0.00521080258755285
                ]
            ],
            "volume_eff": 38.552707183910734,
            "alpha_iso": 12.110798068244208,
            "c6_ii": 47.464504381945176,
            "c8_ii": 1383.4956992466455,
            "c10_ii": 50524.39667463827,
            "slater_b_init": 34.89293799750288
        },
        {
            "index": 1,
            "element": "C",
            "charge": -0.16673086616850874,
            "dipole": [
                0.04033861679101757,
                -0.04437274786181797,
                -0.03240212092233418
            ],
            "quadrupole": [
                [
                    -4.622860218210225,
                    -4.5989721500453005,
                    -0.06109545288638268
                ],
                [
                    -4.5989721500453005,
                    0.02636620813055324,
                    -4.56265925704742
                ],
                [
                    -0.06109545288638268,
                    -4.56265925704742,
                    0.018589121409156122
                ]
            ],
            "volume_eff": 33.917751799739506,
            "alpha_iso": 10.654791141279425,
            "c6_ii": 36.7378136160816,
            "c8_ii": 983.188873040486,
            "c10_ii": 32966.66865244681,
            "slater_b_init": 36.414985893230195
        },
        {
            "index": 2,
            "element": "C",
            "charge": -0.20711867411799645,
            "dipole": [
                -0.04298213145470434,
                0.02997071098329698,
                0.02004217966094787
            ],
            "quadrupole": [
                [
                    -4.75409502539069,
                    -4.687903573228661,
                    -0.05132216519898137
                ],
                [
                    -4.687903573228661,
                    0.03567449847504744,
                    -4.653241052307109
                ],
                [
                    -0.05132216519898137,
                    -4.653241052307109,
                    0.025660945657847458
                ]
            ],
            "volume_eff": 35.009728622143314,
            "alpha_iso": 10.997820509573815,
            "c6_ii": 39.14142922064857,
            "c8_ii": 1069.8793018966069,
            "c10_ii": 36639.31549511224,
            "slater_b_init": 36.03237736548338
        },
        {
            "index": 3,
            "element": "C",
            "charge": -0.3177990932262773,
            "dipole": [
                0.011275368164396485,
                -0.03425010770283736,
                -0.027426637255927443
            ],
            "quadrupole": [
                [
                    -4.902376454436796,
                    -4.8849731247127375,
                    -0.04697615193090931
                ],
                [
                    -4.8849731247127375,
                    0.02413159000321782,
                    -4.85119796633137
                ],
                [
                    -0.04697615193090931,
                    -4.85119796633137,
                    0.020669219644082814
                ]
            ],
            "volume_eff": 36.59611689774678,
            "alpha_iso": 11.496162376255533,
            "c6_ii": 42.769010563649104,
            "c8_ii": 1204.0877846332414,
            "c10_ii": 42471.887070647615,
            "slater_b_init": 35.504017307272356
        },
        {
            "index": 4,
            "element": "C",
            "charge": 0.10284278891038845,
            "dipole": [
                -0.024369162562737915,
                0.061215401958668945,
                0.0917518043481583
            ],
            "quadrupole": [
                [
                    -4.214695095136768,
                    -4.134429773078631,
                    0.06887636488241877
                ],
                [
                    -4.134429773078631,
                    -0.006949454065836055,
                    -4.101534222186881
                ],
                [
                    0.06887636488241877,
                    -4.101534222186881,
                    0.01581900846987411
                ]
            ],
            "volume_eff": 30.019206759372427,
            "alpha_iso": 9.430117306609139,
            "c6_ii": 28.77780165697687,
            "c8_ii": 709.9526200228433,
            "c10_ii": 21943.989016873027,
            "slater_b_init": 37.92766397411882
        },
        {
            "index": 5,
            "element": "O",
            "charge": -0.41227445499152715,
            "dipole": [
                -0.027452804644718547,
                -0.07907292899576607,
                0.003588357904567915
            ],
            "quadrupole": [
                [
                    -4.086428985629531,
                    -4.031196173763999,
                    0.02062982247372064
                ],
                [
                    -4.031196173763999,
                    0.017353394931643704,
                    -4.113632749965321
                ],
                [
                    0.02062982247372064,
                    -4.113632749965321,
                    0.0037277042924343143
                ]
            ],
            "volume_eff": 23.252314511710882,
            "alpha_iso": 6.9371546057038,
            "c6_ii": 25.745410794431546,
            "c8_ii": 1053.1592901799302,
            "c10_ii": 41485.648585942035,
            "slater_b_init": 34.03605260010356
        },
        {
            "index": 6,
            "element": "C",
            "charge": 0.9725048878790918,
            "dipole": [
                0.0014311157562374075,
                -0.0326484682770916,
                -0.014760429550543467
            ],
            "quadrupole": [
                [
                    -2.8107367480869696,
                    -2.979504693428811,
                    -0.03227571921706193
                ],
                [
                    -2.979504693428811,
                    -0.006833720268323168,
                    -2.9250218216875092
                ],
                [
                    -0.03227571921706193,
                    -2.9250218216875092,
                    0.014391554660847058
                ]
            ],
            "volume_eff": 19.706819875212087,
            "alpha_iso": 6.190624044569241,
            "c6_ii": 12.402015933693512,
            "c8_ii": 231.10477894394975,
            "c10_ii": 5395.603493307411,
            "slater_b_init": 43.63989024251187
        },
        {
            "index": 7,
            "element": "O",
            "charge": -0.6144740818459908,
            "dipole": [
                -0.0008650619292267428,
                0.15690495815968503,
                0.07381230758959936
            ],
            "quadrupole": [
                [
                    -4.333604103585372,
                    -4.426729981213406,
                    0.01746110250266845
                ],
                [
                    -4.426729981213406,
                    -0.013625224997266273,
                    -4.454262677649939
                ],
                [
                    0.01746110250266845,
                    -4.454262677649939,
                    0.029607657773198855
                ]
            ],
            "volume_eff": 25.809410491524456,
            "alpha_iso": 7.700045119018346,
            "c6_ii": 31.719301763536507,
            "c8_ii": 1390.9956981002454,
            "c10_ii": 58740.48647156326,
            "slater_b_init": 32.872688218730964
        },
        {
            "index": 8,
            "element": "O",
            "charge": -0.4169534517124518,
            "dipole": [
                0.02563911725863165,
                -0.0511137035171478,
                -0.060753818594946475
            ],
            "quadrupole": [
                [
                    -4.099580797883327,
                    -4.057855766480172,
                    0.04679184932817623
                ],
                [
                    -4.057855766480172,
                    -0.019164080417459928,
                    -4.088456729744228
                ],
                [
                    0.04679184932817623,
                    -4.088456729744228,
                    -0.006269317916753595
                ]
            ],
            "volume_eff": 23.28804788897331,
            "alpha_iso": 6.947815392290379,
            "c6_ii": 25.824600964177467,
            "c8_ii": 1057.480712189349,
            "c10_ii": 41698.54237093393,
            "slater_b_init": 34.01863528649983
        },
        {
            "index": 9,
            "element": "C",
            "charge": 0.14066617479526133,
            "dipole": [
                0.01862057897527795,
                0.10921642400715961,
                -0.012077016829873645
            ],
            "quadrupole": [
                [
                    -4.134912204891842,
                    -3.946978185787492,
                    -0.00879472106933792
                ],
                [
                    -3.946978185787492,
                    -0.016780561529234423,
                    -4.111009849515218
                ],
                [
                    -0.00879472106933792,
                    -4.111009849515218,
                    0.015900232431054144
                ]
            ],
            "volume_eff": 29.201546692795837,
            "alpha_iso": 9.173260741192408,
            "c6_ii": 27.2314583914377,
            "c8_ii": 659.5490218737345,
            "c10_ii": 20014.176258935546,
            "slater_b_init": 38.278409161219514
        },
        {
            "index": 10,
            "element": "C",
            "charge": -0.3402211382465552,
            "dipole": [
                -0.015374260688895691,
                -0.03967384417492883,
                -0.010252780390812606
            ],
            "quadrupole": [
                [
                    -4.9137581679371465,
                    -4.891763310907456,
                    -0.05573379734267845
                ],
                [
                    -4.891763310907456,
                    -0.011977062937908976,
                    -4.903909297076065
                ],
                [
                    -0.05573379734267845,
                    -4.903909297076065,
                    -0.005628204453932662
                ]
            ],
            "volume_eff": 36.764015530238005,
            "alpha_iso": 11.548905402169007,
            "c6_ii": 43.16234906286374,
            "c8_ii": 1218.875393835724,
            "c10_ii": 43124.89062673788,
            "slater_b_init": 35.449886716397366
        },
        {
            "index": 11,
            "element": "C",
            "charge": 0.03269634429907686,
            "dipole": [
                0.01568428932394918,
                -0.015710003459120946,
                0.043933343080736216
            ],
            "quadrupole": [
                [
                    -4.288110436763068,
                    -4.290137058844431,
                    0.00039652299609433273
                ],
                [
                    -4.290137058844431,
                    -0.007082414019988258,
                    -4.232276637575268
                ],
                [
                    0.00039652299609433273,
                    -4.232276637575268,
                    -0.003649993431383437
                ]
            ],
            "volume_eff": 31.075661109993387,
            "alpha_iso": 9.761987783243995,
            "c6_ii": 30.83897566234413,
            "c8_ii": 778.5487382729394,
            "c10_ii": 24625.56059709636,
            "slater_b_init": 37.49290053865781
        },
        {
            "index": 12,
            "element": "C",
            "charge": -0.4713197017796551,
            "dipole": [
                0.03997781504429032,
                0.05442915175083543,
                -0.01907649614524783
            ],
            "quadrupole": [
                [
                    -5.169993773049085,
                    -5.234457158002723,
                    0.04093310564333245
                ],
                [
                    -5.234457158002723,
                    -0.033099128927802646,
                    -5.2152361897587545
                ],
                [
                    0.04093310564333245,
                    -5.2152361897587545,
                    0.026625441218261672
                ]
            ],
            "volume_eff": 39.768533590452506,
            "alpha_iso": 12.492733065063614,
            "c6_ii": 50.50546167824938,
            "c8_ii": 1502.9239553459793,
            "c10_ii": 56033.80673899629,
            "slater_b_init": 34.53366244128975
        },
        {
            "index": 13,
            "element": "C",
            "charge": -0.4609702897364123,
            "dipole": [
                -0.05910665962229346,
                -0.002841194378393465,
                0.012281776135150078
            ],
            "quadrupole": [
                [
                    -5.242555748622033,
                    -5.155997251154925,
                    -0.005649883392709116
                ],
                [
                    -5.155997251154925,
                    0.013799062968120062,
                    -5.147438664823695
                ],
                [
                    -0.005649883392709116,
                    -5.147438664823695,
                    -0.015647006112060022
                ]
            ],
            "volume_eff": 39.49297476821929,
            "alpha_iso": 12.406170084257367,
            "c6_ii": 49.807975118289896,
            "c8_ii": 1475.313765885442,
            "c10_ii": 54750.030173048464,
            "slater_b_init": 34.613794906338214
        },
        {
            "index": 14,
            "element": "H",
            "charge": 0.12972532023705718,
            "dipole": [
                0.020783434092738085,
                0.014927020862013873,
                -0.03970982669717721
            ],
            "quadrupole": [
                [
                    -0.5101064710525589,
                    -0.49840708246074455,
                    0.0029499959410647816
                ],
                [
                    -0.49840708246074455,
                    0.0031470958398334336,
                    -0.5141141238849504
                ],
                [
                    0.0029499959410647816,
                    -0.5141141238849504,
                    0.005614161072111173
                ]
            ],
            "volume_eff": 2.8944645428711344,
            "alpha_iso": 0.9237652796397238,
            "c6_ii": 0.27391234059955905,
            "c8_ii": 1.8242514642153107,
            "c10_ii": 16.768644707717197,
            "slater_b_init": 67.80737795113374
        },
        {
            "index": 15,
            "element": "H",
            "charge": 0.13083273341130264,
            "dipole": [
                0.01933743977302917,
                -0.03346423601170317,
                0.026092820565761704
            ],
            "quadrupole": [
                [
                    -0.5084892043765639,
                    -0.5092657661207872,
                    0.006825197099131499
                ],
                [
                    -0.5092657661207872,
                    0.005667318120262975,
                    -0.49990125494253274
                ],
                [
                    0.006825197099131499,
                    -0.49990125494253274,
                    0.0013543232424270573
                ]
            ],
            "volume_eff": 2.881739239197243,
            "alpha_iso": 0.9197040125097584,
            "c6_ii": 0.2715091634109913,
            "c8_ii": 1.8029425718475691,
            "c10_ii": 16.524162250274777,
            "slater_b_init": 67.90704027455328
        },
        {
            "index": 16,
            "element": "H",
            "charge": 0.13424698074791785,
            "dipole": [
                -0.04888556469477903,
                0.0042669624161867205,
                0.0022291250329747876
            ],
            "quadrupole": [
                [
                    -0.506908223632126,
                    -0.49512540417149237,
                    0.0043184882656990544
                ],
                [
                    -0.49512540417149237,
                    -0.0027876708510868316,
                    -0.49769846492186387
                ],
                [
                    0.0043184882656990544,
                    -0.49769846492186387,
                    -0.0019766285821632033
                ]
            ],
            "volume_eff": 2.827853454353541,
            "alpha_iso": 0.9025064216021941,
            "c6_ii": 0.26145017119584113,
            "c8_ii": 1.7144354790519498,
            "c10_ii": 15.516491062164997,
            "slater_b_init": 68.33566037713055
        },
        {
            "index": 17,
            "element": "H",
            "charge": 0.1104426456671821,
            "dipole": [
                -0.014717136318828651,
                0.037082059352098184,
                -0.031139648323700787
            ],
            "quadrupole": [
                [
                    -0.5092472390042387,
                    -0.5233975076970442,
                    0.005867080942025354
                ],
                [
                    -0.5233975076970442,
                    0.01077280064000848,
                    -0.51283453946031
                ],
                [
                    0.005867080942025354,
                    -0.51283453946031,
                    0.0031811985069195503
                ]
            ],
            "volume_eff": 2.9233137413503627,
            "alpha_iso": 0.9329724706437328,
            "c6_ii": 0.27939973340068947,
            "c8_ii": 1.8731413653543691,
            "c10_ii": 17.33226326310097,
            "slater_b_init": 67.58358409010484
        },
        {
            "index": 18,
            "element": "H",
            "charge": 0.10946871058716101,
            "dipole": [
                -0.01656344222591495,
                -0.018950594483138544,
                0.04440448965590561
            ],
            "quadrupole": [
                [
                    -0.5104867232128656,
                    -0.5121654979604952,
                    0.0017267230376605896
                ],
                [
                    -0.5121654979604952,
                    0.005949961193473711,
                    -0.5274718446807795
                ],
                [
                    0.0017267230376605896,
                    -0.5274718446807795,
                    0.009820001668853306
                ]
            ],
            "volume_eff": 2.9351892419464636,
            "alpha_iso": 0.9367625240254671,
            "c6_ii": 0.2816743788504032,
            "c8_ii": 1.8935016963836147,
            "c10_ii": 17.568076213854035,
            "slater_b_init": 67.49231527502035
        },
        {
            "index": 19,
            "element": "H",
            "charge": 0.10453129851634646,
            "dipole": [
                0.00822180092762089,
                0.013274448841472702,
                -0.04586894627566152
            ],
            "quadrupole": [
                [
                    -0.5220570700820092,
                    -0.5215259355670943,
                    0.00414794638537356
                ],
                [
                    -0.5215259355670943,
                    0.004622097333365976,
                    -0.5346724046840736
                ],
                [
                    0.00414794638537356,
                    -0.5346724046840736,
                    0.01171796848131986
                ]
            ],
            "volume_eff": 3.0126119367396855,
            "alpha_iso": 0.9614718947041551,
            "c6_ii": 0.296730040888345,
            "c8_ii": 2.029634921825874,
            "c10_ii": 19.16083769240323,
            "slater_b_init": 66.90911692299363
        },
        {
            "index": 20,
            "element": "H",
            "charge": 0.11128428323785866,
            "dipole": [
                0.007332279282241808,
                -0.039549953533381955,
                0.028453024591972603
            ],
            "quadrupole": [
                [
                    -0.516016849126411,
                    -0.5227894919019103,
                    0.0063986591246783
                ],
                [
                    -0.5227894919019103,
                    0.011184846562174638,
                    -0.514129036293151
                ],
                [
                    0.0063986591246783,
                    -0.514129036293151,
                    0.002109894000510075
                ]
            ],
            "volume_eff": 2.9486107014772696,
            "alpha_iso": 0.9410459685565755,
            "c6_ii": 0.28425623936236005,
            "c8_ii": 1.9166783900384505,
            "c10_ii": 17.837280488495264,
            "slater_b_init": 67.38975587079426
        },
        {
            "index": 21,
            "element": "H",
            "charge": 0.14436962854860047,
            "dipole": [
                -0.018600446744541213,
                -0.01184486875533061,
                0.04184613128327949
            ],
            "quadrupole": [
                [
                    -0.4802442719572346,
                    -0.4794304285542281,
                    0.003106507153380036
                ],
                [
                    -0.4794304285542281,
                    0.003442879084763388,
                    -0.48920841243455304
                ],
                [
                    0.003106507153380036,
                    -0.48920841243455304,
                    0.009748876051032519
                ]
            ],
            "volume_eff": 2.705512977458396,
            "alpha_iso": 0.863461588550552,
            "c6_ii": 0.23931745416615197,
            "c8_ii": 1.5237079626922063,
            "c10_ii": 13.38965093029825,
            "slater_b_init": 69.35053595411027
        },
        {
            "index": 22,
            "element": "H",
            "charge": 0.1411210540796204,
            "dipole": [
                -0.01856009210618774,
                0.03600557200067607,
                -0.023637268960625873
            ],
            "quadrupole": [
                [
                    -0.48280103822767906,
                    -0.48844308692773,
                    0.0067924000067238
                ],
                [
                    -0.48844308692773,
                    0.008529822049275423,
                    -0.48452626131567333
                ],
                [
                    0.0067924000067238,
                    -0.48452626131567333,
                    0.0017519482280164583
                ]
            ],
            "volume_eff": 2.7199334072601618,
            "alpha_iso": 0.8680638533809028,
            "c6_ii": 0.24187538508900044,
            "c8_ii": 1.5454613079327277,
            "c10_ii": 13.629023939118278,
            "slater_b_init": 69.22775879055544
        },
        {
            "index": 23,
            "element": "H",
            "charge": 0.12458757556076294,
            "dipole": [
                0.021164056950814834,
                -0.05019405546071459,
                0.021180763830079986
            ],
            "quadrupole": [
                [
                    -0.4751608635877498,
                    -0.4830654348856729,
                    0.008457640687677343
                ],
                [
                    -0.4830654348856729,
                    0.004189534919404557,
                    -0.47317007276489687
                ],
                [
                    0.008457640687677343,
                    -0.47317007276489687,
                    -0.004912230102790503
                ]
            ],
            "volume_eff": 2.616845774420186,
            "alpha_iso": 0.835163545027719,
            "c6_ii": 0.22388829408055477,
            "c8_ii": 1.3941550872607071,
            "c10_ii": 11.982044920730651,
            "slater_b_init": 70.12512572466929
        },
        {
            "index": 24,
            "element": "H",
            "charge": 0.11262562657790154,
            "dipole": [
                -0.02040282092691018,
                -0.013530906569757178,
                -0.052359589781273135
            ],
            "quadrupole": [
                [
                    -0.4883224838781563,
                    -0.4837267008274854,
                    -0.0055305301124050224
                ],
                [
                    -0.4837267008274854,
                    -0.003411571248990328,
                    -0.5056064682659902
                ],
                [
                    -0.0055305301124050224,
                    -0.5056064682659902,
                    -0.006411196776479866
                ]
            ],
            "volume_eff": 2.7306295367631823,
            "alpha_iso": 0.8714775117329305,
            "c6_ii": 0.24378147394891014,
            "c8_ii": 1.5617211895943681,
            "c10_ii": 13.80849866432969,
            "slater_b_init": 69.13724999011919
        },
        {
            "index": 25,
            "element": "H",
            "charge": 0.14041157446131036,
            "dipole": [
                0.01580766756881249,
                -0.0075596667519229575,
                0.0423790451128754
            ],
            "quadrupole": [
                [
                    -0.4822111950540539,
                    -0.4855201677440962,
                    0.004493279249440482
                ],
                [
                    -0.4855201677440962,
                    -0.005666157222617116,
                    -0.4976365919288023
                ],
                [
                    0.004493279249440482,
                    -0.4976365919288023,
                    -0.0070195483450051655
                ]
            ],
            "volume_eff": 2.7481709250670545,
            "alpha_iso": 0.87707582714906,
            "c6_ii": 0.24692360704690622,
            "c8_ii": 1.5886176674728725,
            "c10_ii": 14.106404038822967,
            "slater_b_init": 68.98983644376214
        },
        {
            "index": 26,
            "element": "H",
            "charge": 0.14978591931265905,
            "dipole": [
                0.020605329814932172,
                0.03471366455855239,
                -0.0251849087951298
            ],
            "quadrupole": [
                [
                    -0.47344094980624635,
                    -0.4832343302502543,
                    0.004008511913185107
                ],
                [
                    -0.4832343302502543,
                    -0.009700211714802464,
                    -0.4788671395761629
                ],
                [
                    0.004008511913185107,
                    -0.4788671395761629,
                    0.00042368420971954454
                ]
            ],
            "volume_eff": 2.6771840100422604,
            "alpha_iso": 0.8544204287368916,
            "c6_ii": 0.23433198759402804,
            "c8_ii": 1.4815330350638023,
            "c10_ii": 12.927997468082372,
            "slater_b_init": 69.59429206246435
        },
        {
            "index": 27,
            "element": "H",
            "charge": 0.09796310312724288,
            "dipole": [
                -0.009737224858199688,
                0.0007108464840187496,
                -0.04910623014215106
            ],
            "quadrupole": [
                [
                    -0.5151726387558149,
                    -0.5047242248881617,
                    0.0027557507239175695
                ],
                [
                    -0.5047242248881617,
                    0.001425572070137883,
                    -0.5331227951940588
                ],
                [
                    0.0027557507239175695,
                    -0.5331227951940588,
                    -0.011763096179599733
                ]
            ],
            "volume_eff": 2.9208384730428008,
            "alpha_iso": 0.9321824913966386,
            "c6_ii": 0.2789267793694759,
            "c8_ii": 1.868914877292256,
            "c10_ii": 17.283392197940632,
            "slater_b_init": 67.60266996465603
        },
        {
            "index": 28,
            "element": "H",
            "charge": 0.14742156237498594,
            "dipole": [
                0.022678384598514265,
                -0.03028138310060816,
                -0.0261979035078803
            ],
            "quadrupole": [
                [
                    -0.48612744156910037,
                    -0.4893647946268659,
                    -0.005757409262934956
                ],
                [
                    -0.4893647946268659,
                    0.0063603892585467735,
                    -0.48458677199738825
                ],
                [
                    -0.005757409262934956,
                    -0.48458677199738825,
                    -0.0012352891001752712
                ]
            ],
            "volume_eff": 2.7413218928690006,
            "alpha_iso": 0.8748899658092556,
            "c6_ii": 0.24569436739650283,
            "c8_ii": 1.5780817784395542,
            "c10_ii": 13.989557097912588,
            "slater_b_init": 69.04724434878413
        },
        {
            "index": 29,
            "element": "H",
            "charge": 0.13589908385096428,
            "dipole": [
                -0.04604969861272619,
                0.0075597992310840485,
                -0.010207619365271378
            ],
            "quadrupole": [
                [
                    -0.5011628325048761,
                    -0.48764889068312095,
                    -0.0013694342884336408
                ],
                [
                    -0.48764889068312095,
                    -0.0029584158830749515,
                    -0.49975524990269937
                ],
                [
                    -0.0013694342884336408,
                    -0.49975524990269937,
                    -0.000596157856624904
                ]
            ],
            "volume_eff": 2.801691364548994,
            "alpha_iso": 0.8941568184730833,
            "c6_ii": 0.25663489896999464,
            "c8_ii": 1.6724643044421612,
            "c10_ii": 15.043128154817932,
            "slater_b_init": 68.54770699794743
        },
        {
            "index": 30,
            "element": "H",
            "charge": 0.13842303754307417,
            "dipole": [
                0.01816570584770108,
                0.002115415104745884,
                0.041084097301773724
            ],
            "quadrupole": [
                [
                    -0.5006582750343265,
                    -0.49281906576147794,
                    -0.0026384484857065755
                ],
                [
                    -0.49281906576147794,
                    0.005000876256453798,
                    -0.5101558937402405
                ],
                [
                    -0.0026384484857065755,
                    -0.5101558937402405,
                    -0.0013241821701695836
                ]
            ],
            "volume_eff": 2.8590878083412274,
            "alpha_iso": 0.9124748324493279,
            "c6_ii": 0.2672576335331994,
            "c8_ii": 1.7653984038594288,
            "c10_ii": 16.09516731345703,
            "slater_b_init": 68.0859023630779
        },
        {
            "index": 31,
            "element": "H",
            "charge": 0.14180025599471802,
            "dipole": [
                0.008539355909352982,
                -0.0040206600653192,
                0.043834441772948894
            ],
            "quadrupole": [
                [
                    -0.4853321467325339,
                    -0.49544904211440066,
                    0.00028660092155264585
                ],
                [
                    -0.49544904211440066,
                    0.0006166175846622328,
                    -0.5032469173275784
                ],
                [
                    0.00028660092155264585,
                    -0.5032469173275784,
                    -0.005772142102382521
                ]
            ],
            "volume_eff": 2.8048950981535956,
            "alpha_iso": 0.8951792866447645,
            "c6_ii": 0.25722215847140206,
            "c8_ii": 1.677569065859306,
            "c10_ii": 15.100544070925208,
            "slater_b_init": 68.52159880142086
        },
        {
            "index": 32,
            "element": "H",
            "charge": 0.13998731796662545,
            "dipole": [
                0.006166957186184717,
                -0.03779197845669692,
                -0.025922175006119832
            ],
            "quadrupole": [
                [
                    -0.48716219324104787,
                    -0.5021434903699515,
                    -0.002143408425427227
                ],
                [
                    -0.5021434903699515,
                    0.004687088894598599,
                    -0.49657630026294863
                ],
                [
                    -0.002143408425427227,
                    -0.49657630026294863,
                    0.002585298264510249
                ]
            ],
            "volume_eff": 2.802601670218595,
            "alpha_iso": 0.8944473415591261,
            "c6_ii": 0.25680169404169,
            "c8_ii": 1.6739137774362618,
            "c10_ii": 15.059426686279815,
            "slater_b_init": 68.5402845941948
        },
        {
            "index": 33,
            "element": "H",
            "charge": 0.13830323813577827,
            "dipole": [
                0.010367073306943765,
                0.04030374058147121,
                -0.020882208432499345
            ],
            "quadrupole": [
                [
                    -0.49106799053563255,
                    -0.5037819645025445,
                    0.0009063383455912919
                ],
                [
                    -0.5037819645025445,
                    -0.005658916747080663,
                    -0.49821999684169266
                ],
                [
                    0.0009063383455912919,
                    -0.49821999684169266,
                    0.0022552638668448238
                ]
            ],
            "volume_eff": 2.8220597666463885,
            "alpha_iso": 0.9006573723339537,
            "c6_ii": 0.26037995383737106,
            "c8_ii": 1.705084732587907,
            "c10_ii": 15.410777167860106,
            "slater_b_init": 68.38239277340487
        }
    ]
}